billarchive/__init__.py
billarchive/__main__.py
billarchive/billarchive.py
billarchive-0.4.dist-info/METADATA
billarchive-0.4.dist-info/WHEEL
billarchive-0.4.dist-info/entry_points.txt
billarchive-0.4.dist-info/licenses/COPYING.wtfpl
billarchive-0.4.dist-info/RECORD
