Metadata-Version: 2.1
Name: billarchive
Version: 0.4
Summary: Command-line automated bills downloading
Project-URL: Homepage, https://gitlab.com/hydrargyrum/billarchive
Author-email: Hg <dev@indigo.re>
License-Expression: WTFPL
License-File: COPYING.wtfpl
Classifier: Development Status :: 4 - Beta
Classifier: Environment :: Console
Classifier: Intended Audience :: End Users/Desktop
Classifier: License :: Public Domain
Classifier: Operating System :: OS Independent
Classifier: Programming Language :: Python
Classifier: Programming Language :: Python :: 3.6
Classifier: Programming Language :: Python :: 3.7
Classifier: Programming Language :: Python :: 3.8
Classifier: Programming Language :: Python :: 3.9
Classifier: Topic :: Home Automation
Classifier: Topic :: Internet :: WWW/HTTP :: Indexing/Search
Classifier: Topic :: Office/Business :: Financial :: Accounting
Classifier: Topic :: System :: Archiving :: Backup
Requires-Python: >=3.6
Requires-Dist: python-dateutil
Requires-Dist: python-magic
Requires-Dist: woob
